setup.py
Drive_share_library/__init__.py
Drive_share_library/utilities.py
Drive_share_library.egg-info/PKG-INFO
Drive_share_library.egg-info/SOURCES.txt
Drive_share_library.egg-info/dependency_links.txt
Drive_share_library.egg-info/not-zip-safe
Drive_share_library.egg-info/top_level.txt