Metadata-Version: 2.1
Name: Drive_share_library
Version: 0.1
Summary: route and cost calculation library
Author-email: palnatisaikumarreddy150@gmail.com
